workflow_engine/__init__.py
workflow_engine/processor.py
workflow_engine/status_exception.py
workflow_engine/task.py
workflow_engine/time_block.py
workflow_engine/workflow_model.py
workflow_engine-0.1.0.dist-info/LICENSE
workflow_engine-0.1.0.dist-info/METADATA
workflow_engine-0.1.0.dist-info/WHEEL
workflow_engine-0.1.0.dist-info/top_level.txt
workflow_engine-0.1.0.dist-info/RECORD
