Metadata-Version: 2.1
Name: workflow-engine
Version: 0.1.0
Summary: a engine to process workflows and tasks
Author: Deutsche Telekom IT GmbH
License: Apache Software License (Apache 2.0)
Keywords: python,workflow,engine
Classifier: Intended Audience :: Developers
Classifier: Programming Language :: Python :: 3
Classifier: License :: OSI Approved :: Apache Software License
Classifier: Natural Language :: English
Classifier: Operating System :: OS Independent
Classifier: Development Status :: 4 - Beta
License-File: LICENSE
